[
  {
    "date" : "2024-04-15T19:42:58.990Z",
    "chat" : "1288",
    "id" : "2935",
    "message" : "Hola qué pasa",
    "avatar" : "Mock Avatar",
    "nick" : "Pepe",
    "source" : "594"
  },
  {
    "chat" : "1202",
    "date" : "2024-04-20T11:13:03.396Z",
    "nick" : "ffffhhhh",
    "message" : "Che",
    "source" : "404",
    "avatar" : "images\/404_2024315134421.png",
    "id" : "2936"
  },
  {
    "source" : "404",
    "avatar" : "images\/404_2024315134421.png",
    "message" : "Que diuen? ",
    "chat" : "1202",
    "date" : "2024-04-20T11:13:14.937Z",
    "id" : "2937",
    "nick" : "ffffhhhh"
  },
  {
    "avatar" : "images\/404_2024315134421.png",
    "id" : "2938",
    "message" : "Holi",
    "chat" : "1202",
    "date" : "2024-04-20T11:45:46.183Z",
    "nick" : "ffffhhhh",
    "source" : "404"
  },
  {
    "chat" : "1138",
    "source" : "404",
    "date" : "2024-05-02T14:10:38.621Z",
    "nick" : "ffffhhhh",
    "message" : "Mamamam",
    "avatar" : "images\/404_2024315134421.png",
    "id" : "2940"
  },
  {
    "nick" : "tester102",
    "id" : "2941",
    "message" : "Mensaje nuevo",
    "chat" : "1292",
    "source" : "601",
    "date" : "2024-05-07T06:57:02.536Z",
    "avatar" : ""
  },
  {
    "avatar" : "",
    "nick" : "tester102",
    "message" : "Aaa",
    "source" : "601",
    "date" : "2024-05-07T06:59:47.616Z",
    "id" : "2943",
    "chat" : "1295"
  }
]
